AUTHORS
LICENSE
MANIFEST.in
README.rst
setup.py
django_generic_aggregation.egg-info/PKG-INFO
django_generic_aggregation.egg-info/SOURCES.txt
django_generic_aggregation.egg-info/dependency_links.txt
django_generic_aggregation.egg-info/top_level.txt
generic_aggregation/__init__.py
generic_aggregation/utils.py
generic_aggregation_tests/__init__.py
generic_aggregation_tests/models.py
generic_aggregation_tests/tests.py
generic_aggregation_tests/migrations/0001_initial.py
generic_aggregation_tests/migrations/__init__.py