Metadata-Version: 1.1
Name: django-generic-aggregation
Version: 0.4.0
Summary: annotate() and aggregate() for generically related data
Home-page: http://github.com/coleifer/django-generic-aggregation/
Author: Charles Leifer
Author-email: coleifer@gmail.com
License: UNKNOWN
Platform: UNKNOWN
Classifier: Development Status :: 4 - Beta
Classifier: Environment :: Web Environment
Classifier: Intended Audience :: Developers
Classifier: License :: OSI Approved :: MIT License
Classifier: Operating System :: OS Independent
Classifier: Programming Language :: Python
Classifier: Framework :: Django
